{
  "comments": [
    {
      "timestamp": 1584915536,
      "data": [
        {
          "comment": {
            "timestamp": 1584915536,
            "comment": "Thanks, Uncle Dave!",
            "author": "Andy Kuck"
          }
        }
      ],
      "title": "Andy Kuck commented on David Kuck's post."
    },
    {
      "timestamp": 1584915110,
      "data": [
        {
          "comment": {
            "timestamp": 1584915110,
            "comment": "\u00f0\u009f\u0098\u0085",
            "author": "Andy Kuck"
          }
        }
      ],
      "title": "Andy Kuck commented on Justin Bell's post."
    },
    {
      "timestamp": 1525648850,
      "data": [
        {
          "comment": {
            "timestamp": 1525648850,
            "comment": "Thanks! I've been busy, but I'll start reading and posting things on this page more often. I'm a high school math teacher in Hammond, IN. I started writing children's stories a couple years ago, when I was subbing in elementary schools. Since then I've written a number of rhyming picture book stories. I'm always looking to get feedback on them, and to read what sorts of things other people are writing for children.",
            "author": "Andy Kuck",
            "group": "Central IL Critique Group"
          }
        }
      ],
      "title": "Andy Kuck commented on Melissa Durbin's post."
    },
    {
      "timestamp": 1504410733,
      "data": [
        {
          "comment": {
            "timestamp": 1504410733,
            "comment": "It's unlikely that whatever I was making could have been called music.",
            "author": "Andy Kuck"
          }
        }
      ],
      "title": "Andy Kuck commented on Richard Norman's post."
    },
    {
      "timestamp": 1500483289,
      "data": [
        {
          "comment": {
            "timestamp": 1500483290,
            "comment": "Thanks!",
            "author": "Andy Kuck"
          }
        }
      ],
      "title": "Andy Kuck commented on Karen Spoor's post."
    },
    {
      "timestamp": 1500482987,
      "data": [
        {
          "comment": {
            "timestamp": 1500482987,
            "comment": "Thanks! I'm glad you liked it.",
            "author": "Andy Kuck"
          }
        }
      ],
      "title": "Andy Kuck commented on Alicia Thompson's post."
    },
    {
      "timestamp": 1498251004,
      "data": [
        {
          "comment": {
            "timestamp": 1498251004,
            "comment": "Andy Kuck; Ypsilanti, Michigan",
            "author": "Andy Kuck",
            "group": "The Taming of the Shrew"
          }
        }
      ],
      "title": "Andy Kuck commented on Eric Brant's post."
    },
    {
      "timestamp": 1488641163,
      "title": "Andy Kuck replied to a comment."
    },
    {
      "timestamp": 1435175440,
      "data": [
        {
          "comment": {
            "timestamp": 1435175440,
            "comment": "I will, but it's spelled Dndfiosdlonvlcmvwetyue. And she can't leave home now. You'll have visit Pluto to see her. Also, there's no shopping there. They don't even have a word for \"shopping.\"",
            "author": "Andy Kuck"
          }
        }
      ],
      "title": "Andy Kuck commented on Lii Nadia's post."
    },
    {
      "timestamp": 1400453093,
      "data": [
        {
          "comment": {
            "timestamp": 1400453093,
            "comment": "by the way, you've always been better than me at sports and stuff",
            "author": "Andy Kuck"
          }
        }
      ],
      "title": "Andy Kuck commented on his own post."
    },
    {
      "timestamp": 1400453057,
      "data": [
        {
          "comment": {
            "timestamp": 1400453057,
            "comment": "<3",
            "author": "Andy Kuck"
          }
        }
      ],
      "title": "Andy Kuck commented on his own post."
    },
    {
      "timestamp": 1400452956,
      "data": [
        {
          "comment": {
            "timestamp": 1400452955,
            "comment": "seriously though, skip bayless is the greatest sports commentator to ever live",
            "author": "Andy Kuck"
          }
        }
      ],
      "title": "Andy Kuck commented on Deacon Noah Thelen's link."
    },
    {
      "timestamp": 1400452792,
      "data": [
        {
          "comment": {
            "timestamp": 1400452792,
            "comment": "#favoriteshirt",
            "author": "Andy Kuck"
          }
        }
      ],
      "title": "Andy Kuck commented on his own photo."
    },
    {
      "timestamp": 1400452704,
      "data": [
        {
          "comment": {
            "timestamp": 1400452704,
            "comment": "#nextupolympics",
            "author": "Andy Kuck"
          }
        }
      ],
      "title": "Andy Kuck commented on his own post."
    },
    {
      "timestamp": 1400452274,
      "data": [
        {
          "comment": {
            "timestamp": 1400452274,
            "comment": "<3",
            "author": "Andy Kuck"
          }
        }
      ],
      "title": "Andy Kuck commented on his own post."
    },
    {
      "timestamp": 1400451562,
      "data": [
        {
          "comment": {
            "timestamp": 1400451562,
            "comment": "<3",
            "author": "Andy Kuck"
          }
        }
      ],
      "title": "Andy Kuck commented on Deacon Noah Thelen's link."
    },
    {
      "timestamp": 1400451388,
      "data": [
        {
          "comment": {
            "timestamp": 1400451388,
            "comment": "8-0",
            "author": "Andy Kuck"
          }
        }
      ],
      "title": "Andy Kuck commented on his own life event."
    },
    {
      "timestamp": 1400451166,
      "data": [
        {
          "comment": {
            "timestamp": 1400451165,
            "comment": "<3",
            "author": "Andy Kuck"
          }
        }
      ],
      "title": "Andy Kuck commented on Brandon Piotrzkowski's link."
    },
    {
      "timestamp": 1400450901,
      "data": [
        {
          "comment": {
            "timestamp": 1400450901,
            "comment": "<3",
            "author": "Andy Kuck"
          }
        }
      ],
      "title": "Andy Kuck commented on his own post."
    },
    {
      "timestamp": 1389738762,
      "attachments": [
        {
          "data": [
            {
              "external_context": {
                "url": "http://andrewkuckmath495.blogspot.com/"
              }
            }
          ]
        }
      ],
      "data": [
        {
          "comment": {
            "timestamp": 1389738759,
            "comment": "http://andrewkuckmath495.blogspot.com/",
            "author": "Andy Kuck",
            "group": "495 W14"
          }
        }
      ],
      "title": "Andy Kuck commented on John Golden's post."
    }
  ]
}